{
  "purchaseComplete": "購入完了",
  "purchaseFailure": "購入失敗",
  "orderConfirmed": "オーダー確定",
  "orderFailed": "オーダー失敗",
  "thanksPurchase2": "ご購入ありがとうございます。",
  "experienceSoonAvailable": "もう少しですばらしい体験が始まります。",
  "confirmationEmail": "この購入を確認するため、3DEXPERIENCE - Dassault Systèmes から最初のメールが届きます。",
  "getStartedEmail": "3DEXPERIENCE Platform サブスクリプションの準備が完了すると、受信トレイに \"Get started\" というメールが届きます。",
  "checkSpam": " 必要に応じて、迷惑メール フォルダを確認してください。",
  "errorPayment": "支払いにエラーが発生しました。",
  "supportDS": "Dassault Systèmes サポートにお問い合わせください。",
  "visitGetStarted": "{getStarted} にアクセスしてビデオなどを参照し、使用を始めるときお役立てください。"
}
