{
  "information": "Informazioni",
  "addresses": "Indirizzi",
  "members": "Membri",
  "companyName": "nome azienda",
  "country": "paese",
  "selectACountry": "Seleziona un paese",
  "taxRegistrationId": "ID registrazione imposta",
  "registrationId": "ID registrazione",
  "empName": "Nome Marketplace aziendale",
  "empNameInfo": "Questo sarà il nome del servizio visualizzato in 3DCompass.",
  "back": "Indietro",
  "next": "Avanti",
  "finish": "Finitura",
  "shippingAddress": "indirizzo di spedizione:",
  "billingAddress": "indirizzo di fatturazione:",
  "enterBillingAddress": "Immettere l'indirizzo di fatturazione",
  "enterShippingAddress": "Immettere l'indirizzo di spedizione",
  "severalAddressesDefined": "Più indirizzi definiti",
  "manageAddresses": "Gestisci indirizzi",
  "selectBillingAddress": "Selezionare un indirizzo di fatturazione",
  "selectShippingAddress": "Selezionare un indirizzo di spedizione",
  "addAnAddress": "Aggiungi un indirizzo",
  "inviteMembers": "Invita membri",
  "savingError": "Si è verificato un errore durante il salvataggio delle informazioni"
}