{
  "shareInfoMembers": "Condividere questo contenuto con gli utenti della <b>3D</b>EXPERIENCE Platform",
  "shareInfoUsersExt": "Condividere questo contenuto con i membri della <b>3D</b>EXPERIENCE Platform o con i collaboratori esterni inserendo il loro indirizzo e-mail.",
  "can_view": "Autorizzato a visualizzare",
  "can_edit": "Autorizzato a modificare",
  "shareByLinkDescription": "Gli utenti autorizzati possono accedere al contenuto tramite questo collegamento",
  "copyLink": "Copia collegamento",
  "linkCopiedToClipboard": "Il collegamento è stato copiato negli Appunti",
  "allowReshare": "Consenti condivisione con altri",
  "groupMemberCount": "{total} membro",
  "groupMembersCount": "{total} membri",
  "pending": "in sospeso",
  "enterName": "Immettere un nome o eseguire l'accesso",
  "share": "Condividi",
  "addMessage": "Aggiungi un messaggio",
  "enterMessageDescription": "Immettere un messaggio personalizzato"
}