{
  "CreateContent": "콘텐츠 생성",
  "placeholderSearchCommunity": "커뮤니티 검색",
  "placeholderSearchConversation": "대화 검색",
  "SelectMedia": "미디어 선택",
  "DropFilesHere": "여기에 로드할 파일 놓기",
  "CantCreateContent": "이 커뮤니티에서는 콘텐츠를 생성할 수 없습니다.",
  "BecomeAnAuthor": "작성자로 설정",
  "SelectCommunity": "커뮤니티 선택",
  "SelectConversation": "대화 선택",
  "Favorites": "즐겨찾기",
  "Communities": "커뮤니티",
  "NoResult": "결과 없음",
  "EmptyList": "빈 목록",
  "SelectContentType": "콘텐츠 유형 선택",
  "Text": "텍스트",
  "Table": "테이블",
  "Slide": "슬라이드",
  "Sketch": "스케치",
  "Story": "스토리",
  "Whiteboard": "화이트보드",
  "voice": "음성",
  "video": "비디오",
  "FavoriteConversations": "자주 사용하는 대화",
  "MyConversations": "내 대화",
  "OtherConversations": "기타 대화",
  "SuggestedConversations": "제안된 대화",
  "ConversationSearchIssue": "대화 검색에 이슈가 있습니다!",
  "NoCommunityFound": "커뮤니티가 없음",
  "NoConversationFound": "대화가 없음"
}