{
  "Actor.ToolTip": "도구 정보",
  "Actor.Freeze": "동결",
  "Freeze.NoFreeze": "동결하지 않음",
  "Freeze.Freeze": "동결",
  "Freeze.FreezeInPlay": "플레이어에서만 동결",
  "Actor.BomId": "BOM ID",
  "Actor.Prop.Area": "구역",
  "Actor.Prop.Volume": "볼륨",
  "Actor.Texture.Map.Path": "텍스처",
  "Actor.Env.Effect": "환경 효과",
  "Actor.PLM.Material.Choice": "재질",
  "Actor.PLM.Material": "재질",
  "ActorCurve.Width": "너비",
  "ActorPoint.Width": "크기",
  "ActorCompositePmi.MirroringRepresentation": "대칭 표현",
  "material.none": "없음",
  "material.chromic": "크롬",
  "material.metal": "금속",
  "material.metal_brushed": "금속 브러시 처리됨",
  "material.plastic": "플라스틱",
  "material.glass": "유리",
  "material.glass_plastic": "유리 플라스틱",
  "material.chromicII": "크롬 II(색상 포함)",
  "material.unknown": "알 수 없음",
  "material.gold": "금",
  "material.aluminium": "알루미늄",
  "material.satin": "샤틴",
  "Actor.Texture.Blending.Mode": "블렌딩(모듈)",
  "Actor.Texture.Transparency": "투명도",
  "Actor.Texture.Border.Mode": "모자이크",
  "Actor.Texture.UV.Ratio": "비율 높이/너비",
  "Actor.Texture.UV.Scale": "배율",
  "Actor.Texture.Projection.Type": "투영 유형",
  "Actor.Texture.Frame.Gen": "텍스처 투사 매트릭스",
  "Actor.Override.Type": "유형",
  "Actor.Override.Type.None": "없음",
  "Actor.Override.Type.Color": "강조 표시",
  "Actor.Override.Type.Material": "재질",
  "material.texture.projection.uv": "UV",
  "material.texture.projection.planar": "평면형",
  "material.texture.projection.spherical": "구형",
  "material.texture.projection.cubic": "입방",
  "material.texture.projection.finitecylindrical": "유한 원통형",
  "material.texture.projection.infinitecylindrical": "무한 원통형",
  "primitive.type.line": "선",
  "primitive.type.disc": "원반",
  "primitive.type.square": "사각형",
  "primitive.type.cube": "정육면체",
  "primitive.type.sphere": "구",
  "primitive.type.cylinder": "원통",
  "ActorMeshPrimitive.Domain1.DomainType": "기본요소 유형",
  "ActorMeshPrimitive.Domain1.Height": "높이",
  "ActorMeshPrimitive.Cube.Depth": "깊이",
  "ActorMeshPrimitive.Cube.Width": "너비",
  "ActorMeshPrimitive.Domain1.OuterRadius": "반지름",
  "ActorMeshPrimitive.Domain1.TopRadius": "상단 반지름"
}
