{
  ":": ": ",
  "orderSummary": "Order summary",
  "backToCart": "Back to cart",
  "back": "Back",
  "quote": "Quote",
  "subtotal": "Subtotal",
  "taxes": "Taxes",
  "orderTotal": "Order total",
  "taxesCalculatedWithBillingAddress": "Taxes will be calculated with the billing address",
  "totalNotYetAvailable": "Total (including taxes) not available yet",
  "deliveryOnNewPlatform": "Delivery on a new {bold3D}EXPERIENCE platform",
  "deliveryOnPlatform+Name": "Delivery on {bold3D}EXPERIENCE platform {name}",
  "countryChangeInfoMessage": "Your cart has been recalculated based on your billing country.",
  "products": "Products",
  "baselineRequest": "Baseline request",
  "delivery": "Delivery",
  "finish": "Finish",
  "additionalService": "Additional service",
  "pricePerQuote": "Price per quote",
  "pricingStructure": "Pricing structure",
  "quantity": "Quantity",
  "unitPriceTax": "Unit price (tax excl.)",
  "priceTax": "Price (tax excl.)",
  "totalAmountWithTaxes": "Total amount with taxes",
  "item": "Item",
  "items": "Items",
  "unableToDownloadQuote": "Unable to download quote",
  "unableToResetCart": "Unable to reset cart",
  "percentageDiscount": "{percentage}% discount has been applied on eligible items.",
  "savedAmount": "You saved {amount}",
  "couponTerms": "Coupon Terms"
}