{
  "TheRemovedTagIsAlsoPresentInTheContentBody": "Lütfen etiketi içeriğin gövdesinden kaldırmayı unutmayın",
  "TheListOfTagsOnThisContentCouldNotBeUpdated": "Bu içerik üzerindeki etiket listesi güncellenemedi",
  "SubscribeSuccess": "Artık bu içerik etkinliklerine abonesiniz.",
  "SubscribeError": "Bir hata oluştu. Bu içerik etkinliklerine abone değilsiniz.",
  "UnsubscribeSuccess": "Bu içerik etkinliklerine artık abone değilsiniz.",
  "UnsubscribeError": "Bir hata oluştu. Bu içerik etkinliklerine hâlâ abonesiniz.",
  "Other": "Diğer",
  "TODO": "Yapılacaklar",
  "InProgress": "Çalışmada",
  "Done": "Tamamlandı"
}
