{
  "Apriso3DExpExchangeText": "Integration von Delmia Apriso",
  "Apriso3DExpExchangeTooltip": "Konfigurieren Sie den Attributaustausch zwischen Delmia Apriso und 3DExperience",
  "DigitalManufacturingText": "Erstellungsregeln – Artikel und Prozesse",
  "DigitalManufacturingTooltip": "Erstellungsregeln für Artikel und Prozess in 3DEXPERIENCE konfigurieren",
  "DELPPRLifeCycleSyncManagementText": "Lebenszyklusregeln – Fertigungselemente",
  "DELPPRLifeCycleSyncManagementTooltip": "Regeln zum Synchronisieren des Lebenszyklus für MBOM (Elemente)",
  "OperationEngineeringText": "Verfahrenstechnik",
  "OperationEngineeringTooltip": "Verfahrenstechnik konfigurieren",
  "MfgSessionManagementParameterizationText": "Fertigungssitzungsmanagement",
  "MfgSessionManagementParameterizationTooltip": "Fertigungssitzungsmanagement konfigurieren",
  "DELOrderDataMgtText": "Auftragsdatenmanagement",
  "DELOrderDataMgtTooltip": "Auftragsdatenmanagementdienst konfigurieren",
  "DEL3DWorkbookText": "3DWorkbook",
  "DEL3DWorkbookTooltip": "3DWorkbook konfigurieren",
  "DEL3DOperationsViewerText": "Anzeigefunktion 3D-Verfahren",
  "DEL3DOperationsViewerTooltip": "Anzeigefunktion 3D-Verfahren konfigurieren",
  "DELUserExperienceText": "Benutzererlebnis",
  "DELUserExperienceTooltip": "Benutzererlebnis konfigurieren"
}
