{
  "version": "1.0.0",
  "summary": "Odebere hodnotu z daného pole pod daným indexem.",
  "description": "Tento blok poskytne upravené pole jako výstup.<br>Tento blok je dynamický, takže typ pole vstupních dat lze změnit pomocí dialogového okna konfigurace bloku.",
  "dataPorts": {
    "ArrayIn": "pole, které chcete upravit.",
    "Index": "index pole, kde se chcete odebrat hodnotu.",
    "ArrayOut": "upravené pole.",
    "Value": "odebraná hodnota."
  },
  "controlPorts": {
    "In": "vyvolá spuštění bloku.",
    "Out": "aktivuje se po dokončení procesu."
  },
  "example": null
}