{
  "views": {
    "viewLabel": "視圖"
  },
  "commandMenu": {
    "default": "預設視圖",
    "root": "表格視圖",
    "admin": "管理員視圖",
    "user": "我的視圖",
    "widget": "本機視圖"
  },
  "columns": {
    "column_name": "欄名稱",
    "attType": "屬性類型",
    "colName": "欄名稱",
    "pin": "釘選",
    "visibility": "可見度",
    "hide_show": "隱藏/顯示",
    "findinctx": "尋找",
    "thumbnail": "預覽",
    "thumbnails": "預覽",
    "matrixtxt": "位置矩陣",
    "typeName": "類型",
    "extName": "延伸"
  },
  "attributeCategoriesNodes": {
    "COMMON_COLUMNS": "通用欄",
    "TYPE_COLUMNS": "類型欄",
    "EXTENSION_COLUMNS": "延伸欄"
  },
  "ViewManager": {
    "pinLeft": "釘選至左側",
    "pinRight": "釘選至右側",
    "unpinned": "無釘選",
    "title": "所選欄： "
  },
  "AttributeManager": {
    "title": "可用欄： "
  },
  "CreateViewPane": {
    "createview": "建立視圖",
    "message1": "沒有可用的使用者或管理員視圖。",
    "message2": "產生新管理員視圖：",
    "message3": "1. 開啟 Document Management 小工具。",
    "message4": "2. 以管理員認證啟動「設定」表格視圖。"
  },
  "columnsNls": {
    "TITLE": "標題",
    "NAME": "名稱",
    "TYPE": "類型",
    "COLLABORATIVE_POLICY": "協同作業原則",
    "COLLABORATIVE_SPACE": "協同作業空間",
    "REVISION": "修訂版",
    "IS_LATEST_REVISION": "為最新修訂版",
    "FILES": "檔案",
    "LOCK_STATUS": "鎖定狀態",
    "DESCRIPTION": "描述",
    "ORGANIZATION": "組織",
    "OWNER": "擁有者",
    "ORIGINATOR": "產生者",
    "MATURITY": "成熟度",
    "CREATION_DATE": "建立日期",
    "MODIFIED_DATE": "修改日期",
    "COMMENTS": "註解",
    "FILE_TYPE": "檔案類型",
    "APPROVAL_STATUS": "核准狀態"
  },
  "COPY_OF": "以下項目的複本：",
  "AdminViewSaveMessage1": "是否要將其儲存為管理員視圖？",
  "AdminViewSaveMessage2": "否則，它將會儲存為使用者視圖",
  "ViewAlreadyExistWarning": "已存在視圖「{newViewLabel}」。",
  "MaxViewLimitReachedTitle": "已超過限制",
  "MaxViewLimitReachedMsg": "您最多可以建立 4 個 {viewType} 視圖。",
  "commands": {
    "addview": {
      "title": "建立視圖",
      "message1": "您最多可以建立 4 個使用者視圖。",
      "message2": "您最多可以各別建立 4 個使用者/管理員視圖。"
    },
    "removeview": {
      "title": "移除視圖",
      "message": "移除所選視圖。"
    },
    "addColumn": {
      "title": "加入欄",
      "message": "將欄加入至所選欄。"
    },
    "removeColumn": {
      "title": "移除欄",
      "message": "從所選欄中移除欄。"
    },
    "confirm": "確認",
    "cancel": "取消"
  },
  "createNewView": "產生新視圖",
  "Default": "預設"
}
