{
  "_list_conflict_rules": "Pravidla příčin",
  "_list_invalid_Column": "Neplatný sloupec",
  "_conflict_helper": "Pomocný nástroj pro konflikt",
  "_rule": "Pravidlo",
  "_open": "Otevřít",
  "TITLE": "Název",
  "TYPE": "Typ",
  "REVISION": "Oprava",
  "BASEPRICE": "Základní cena",
  "MATURITY_STATE": "Stav dokončení",
  "OWNER": "Odpovědná osoba",
  "MODIFICATION_DATE": "Datum úpravy",
  "ORGANIZATION": "Organizace",
  "COLLABSPACE": "Prostor pro spolupráci",
  "NAME": "Název",
  "EMPTY_CONTENT_MESSAGE": "Ještě nemáte žádnou položku. <br> Vytvořte položku pomocí ikony „+“.",
  "_mandatory_message_matrix_rule": "je povinný údaj.<br>Jedna z hodnot musí být buď Dostupná, Výchozí nebo Vybraná.",
  "_mandatory_message_expression_rule": "je povinné.",
  "_conflict_message": "je v konfliktu",
  "_reason": "Důvod:",
  "_causingRules": "Pravidla příčin",
  "_causingRulesOrBaseConfigurations": "Pravidla příčin / Konfigurace základny",
  "impliedRules": "Implikovaná pravidla"
}
