{
  "sendMessage": "发送消息",
  "swymCall": "3DSwym 通话",
  "startVoiceCall": "开始语音通话",
  "startVideoCall": "开始视频通话",
  "startScreenCall": "开始屏幕共享",
  "addToFavorites": "添加到收藏夹",
  "removeFromFavorites": "从收藏夹中移除",
  "viewProfile": "查看个人资料",
  "blockContact": "屏蔽联系人",
  "removeFromHistory": "从历史记录中移除",
  "clearHistory": "清除历史记录",
  "joinCall": "加入",
  "startCall": "开始语音通话",
  "newCall": "新通话",
  "call": "通话",
  "cancel": "取消",
  "favorites": "收藏夹",
  "suggested": "已建议",
  "voiceCall": "语音通话",
  "videoCall": "视频通话",
  "outgoing": "呼出",
  "incoming": "呼入",
  "missed": "未接",
  "declined": "已拒绝",
  "preferences": "首选项",
  "history": "历史记录",
  "viewMore": "查看更多",
  "viewLess": "查看更少",
  "confirmation": "确认",
  "clearHistoryConfirmation": "是否确定要清除历史记录？",
  "startCallUserLimit": "您最多可以添加 {x} 个用户",
  "startCallUserMaxLimit": "您已达到此通话中的最大用户数",
  "startCallPlaceholder": "键入名称或登录名",
  "conversationTopicPlaceholder": "主题名称",
  "conversationTopicLabel": "为新对话设置主题",
  "notAllUsersAdded": "{x} 个用户未添加",
  "noConversationTopicError": "必须指定主题",
  "searchForPeople": "搜索人员",
  "callInOneClick": "并单击呼叫他们",
  "noCalls": "没有通话",
  "noCallsSoFar": "目前为止没有 {x} 次通话",
  "allCalls": "所有通话",
  "startCallAlertPlaceholder": "{x} 个用户未添加",
  "startCallAlert": "所有用户均未添加",
  "morethan15Members": "超过 15 个成员，不能发起呼叫"
}
