{
  "modifyAttribute.details": "{attributeNLS}: {value} 이전: {replaces}",
  "modifyAttribute.details.ENOStrSpecDesc": "{attributeNLS}",
  "modifyAttribute.details.PLMInstance.V_TreeOrder": "{attributeNLS}",
  "connect.details": "{actionNLS} {typeNLS} <{title} {revision}>",
  "connect.details.VPLMrel/PLMConnection/V_Owner": "{actionNLS} {typeNLS}",
  "connect.details.VPLMrel/PLMPort/V_Owner": "{actionNLS} {typeNLS}",
  "connect.details.Change Coordinator": "{title}",
  "connect.details.Technical Assignee": "{title}",
  "connect.details.Change Contributor": "{title}",
  "connect.details.Change Follower": "{title}",
  "connect.details.Logical Features.Products": "하위 {typeNLS} <{title} {revision}> 추가",
  "connect.details.Product Specification": "사양 추가: <{title} {revision}>",
  "connect.details.Main Derived": "수정된 {relType}: <{title} {revision}>",
  "connect.details.Derived": "파생된 {relType}: <{title} {revision}>",
  "disconnect.details": "{actionNLS} {typeNLS} <{title} {revision}>",
  "disconnect.details.VPLMrel/PLMConnection/V_Owner": "{actionNLS} {typeNLS}",
  "disconnect.details.VPLMrel/PLMPort/V_Owner": "{actionNLS} {typeNLS}",
  "disconnect.details.Change Coordinator": "{title}",
  "disconnect.details.Technical Assignee": "{title}",
  "disconnect.details.Change Contributor": "{title}",
  "disconnect.details.Change Follower": "{title}",
  "disconnect.details.Main Derived": "리비전 삭제됨: {title} {revision}",
  "disconnect.details.Derived": "브랜치 삭제됨: <{title} {revision}>",
  "disconnect.details.Logical Features.Products": "하위 {typeNLS} <{title} {revision}> 제거",
  "disconnect.details.Product Specification": "사양 제: <{title} {revision}>",
  "disconnect.details.Product Configuration": "{typeNLS} 삭제: <{title} {revision}>",
  "disconnect.details.Product Model Type": "{typeNLS} 삭제: <{title} {revision}>",
  "disconnect.details.Associated Manufacturing Plans": "{typeNLS} 삭제: <{title} {revision}>",
  "disconnect.details.Variant Values": "{typeNLS} 삭제: <{title} {revision}>",
  "disconnect.details.Grouped Variability Criteria": "{typeNLS} 삭제: <{title} {revision}>",
  "disconnect.details.Configuration Model Type": "{typeNLS} 삭제: <{title} {revision}>",
  "addPath.details": "{actionNLS} {typeNLS} <{title} {revision}>",
  "addLink.details": "{actionNLS} {typeNLS} <{title} {revision}>",
  "create.details": "{actionNLS} {typeNLS} <{title} {revision}> {revFromText} {rev.typeNLS} <{rev.title} {rev.revision}>",
  "create.details.Person": "{actionNLS} {typeNLS} {title} {revision} {revFromText} {rev.typeNLS} {rev.title} {rev.revision}",
  "create.details.Group Proxy": "{actionNLS} {typeNLS} {title} {revision} {revFromText} {rev.typeNLS} {rev.title} {rev.revision}",
  "create.details.Group": "{actionNLS} {typeNLS} {title} {revision} {revFromText} {rev.typeNLS} {rev.title} {rev.revision}",
  "create.details.Variant": "생성됨",
  "create.details.Variability Group": "생성됨",
  "create.details.Variant Parameter": "생성됨",
  "create.details.Variant Value": "생성됨",
  "create.details.Variability Option": "생성됨",
  "create.details.Product Specification": "생성됨",
  "create.details.Builds": "생성됨",
  "checkin.details": "포맷: {FormatRef} 파일: {FileName}",
  "checkout.details": "포맷: {FormatRef} 파일: {FileName}",
  "removeFile.details": "포맷: {FormatRef} 파일: {FileName}",
  "changeOwner.details": "소유자 {Owner.UserRef} 이전: {Replaces} ",
  "modifyDescription.details": "설명: {Description}",
  "changeName.details": "이름 {ObjectName} 이전: {Replaces}",
  "changeProject.details": "프로젝트: {Project.UserRef} 이전: {Replaces}",
  "changeOrganization.details": "조직: {Organization.UserRef} 이전: {Replaces}",
  "promote.details": "{StateName}(으)로 성숙도 변경",
  "promote.details.Products": "{stateNLS}(으)로 승격",
  "promote.details.Variant": "{stateNLS}(으)로 승격",
  "promote.details.Variability Group": "{stateNLS}(으)로 승격",
  "promote.details.Variant Parameter": "{stateNLS}(으)로 승격",
  "promote.details.Product Configuration": "{stateNLS}(으)로 승격",
  "promote.details.Model Type": "{stateNLS}(으)로 승격",
  "promote.details.Configuration Rule": "{stateNLS}(으)로 승격",
  "promote.details.Manufacturing Plan": "{stateNLS}(으)로 승격",
  "promote.details.Builds": "{stateNLS}(으)로 승격",
  "demote.details": "{StateName}(으)로 성숙도 변경",
  "demote.details.Products": "{stateNLS}(으)로 승격",
  "demote.details.Variant": "{stateNLS}(으)로 승격",
  "demote.details.Variability Group": "{stateNLS}(으)로 승격",
  "demote.details.Variant Parameter": "{stateNLS}(으)로 승격",
  "demote.details.Product Configuration": "{stateNLS}(으)로 승격",
  "demote.details.Model Type": "{stateNLS}(으)로 승격",
  "demote.details.Configuration Rule": "{stateNLS}(으)로 승격",
  "demote.details.Manufacturing Plan": "{stateNLS}(으)로 승격",
  "demote.details.Builds": "{stateNLS}(으)로 승격",
  "modifyState.details": "{StateName}(으)로 성숙도 변경",
  "modifyState.details.Products": "{actionNLS}~{stateNLS}",
  "modifyState.details.Variant": "{actionNLS}~{stateNLS}",
  "modifyState.details.Variability Group": "{actionNLS}~{stateNLS}",
  "modifyState.details.Variant Parameter": "{actionNLS}~{stateNLS}",
  "modifyState.details.Product Configuration": "{actionNLS}~{stateNLS}",
  "modifyState.details.Model Type": "{actionNLS}~{stateNLS}",
  "modifyState.details.Configuration Rule": "{actionNLS}~{stateNLS}",
  "modifyState.details.Manufacturing Plan": "{actionNLS}~{stateNLS}",
  "modifyState.details.Builds": "{actionNLS}~{stateNLS}",
  "reserve.details": "잠근 사용자: {ReservedBy.UserRef}",
  "unreserve.details": "예약되지 않음. 이전: {Was.UserRef}",
  "lock.details": "잠근 사람: {Agent}",
  "unlock.details": "잠금 해제. 이전: {Agent}",
  "addInterface.details": "인터페이스: {Interface}",
  "removeInterface.details": "인터페이스: {Interface}",
  "approve.details": "서명: {SignatureName}  코멘트: {Comment}",
  "changePolicy.details": "정책: {PolicyRef}  이전:  {Replaces}",
  "changeType.details": "유형: {ObjectType}  이전: {Replaces}",
  "changeVault.details": "볼트: {VaultRef}  이전: {Replaces}",
  "ignore.details": "서명: {SignatureName}  코멘트: {Comment}",
  "reject.details": "서명: {SignatureName}  코멘트: {Comment}",
  "grant.details": "피허가자: {Grantee.UserRef}",
  "revoke.details": "피허가자: {Grantee.UserRef}"
}
