{
  "Modifiable.StyleID": "ID de estilo",
  "Modifiable.Style": "Estilo",
  "Modifiable.Style.Exclusion": "Exclusión de estilo",
  "Style.NoStyle": "Sin estilo",
  "Style.Edited.Name": "Se ha editado {originalName} ",
  "Style.SetAsFavorite.Tooltip": "Establecer como favorito",
  "Style.RemoveFromFavorite.Tooltip": "Quitar favorito",
  "Style.CreateNewStyle.Button.Tooltip": "Crear un nuevo estilo basado en las propiedades actuales",
  "Style.CreateNewStyle.html": "Va a crear un nuevo estilo.",
  "Style.CreateNewStyle.Title": "Nombre",
  "Style.CreateNewStyle.PlaceHolder": "Nombre",
  "Style.CreateNewStyle.Dialog.Title": "Creación de un nuevo estilo",
  "Style.CreateNewStyle.Dialog.OK": "Crear",
  "Style.CreateNewStyle.Dialog.Cancel": "Cancelar",
  "Style.UpdateStyle.Button.Tooltip": "Actualizar el estilo según las propiedades actuales",
  "Style.UpdateStyle.html": "<div>Va a actualizar este estilo.</div><div>Afectará a todos los objetos vinculados a este estilo en la presentación</div>",
  "Style.UpdateStyle.Dialog.Title": "Actualizar estilo",
  "Style.UpdateStyle.Dialog.OK": "Actualizar",
  "Style.UpdateStyle.Dialog.Cancel": "Cancelar",
  "Style.UpdateStyle.Dialog.DoNotShowAgain": "No volver a mostrar",
  "Style.RenameStyle.Button.Label": "Cambiar nombre",
  "Style.RenameStyle.Button.Tooltip": "Cambiar nombre del estilo",
  "Style.RenameStyle.html": "Va a cambiar el nombre del estilo",
  "Style.RenameStyle.Title": "Nombre",
  "Style.RenameStyle.PlaceHolder": "Nuevo nombre",
  "Style.RenameStyle.Dialog.Title": "Cambiar el nombre del estilo",
  "Style.RenameStyle.Dialog.OK": "Cambiar nombre",
  "Style.RenameStyle.Dialog.Cancel": "Cancelar",
  "Style.DeleteStyle.Button.Label": "Eliminar",
  "Style.DeleteStyle.Button.Tooltip": "Eliminar estilo",
  "Style.DeleteStyle.html": "<div>Va a eliminar este estilo.</div><div>Afectará a todos los objetos vinculados a este estilo en la presentación</div>",
  "Style.DeleteStyle.Dialog.Title": "Eliminar estilo",
  "Style.DeleteStyle.Dialog.OK": "Eliminar",
  "Style.DeleteStyle.Dialog.Cancel": "Cancelar"
}
