{
  "Meeting_Relations": "Toplantı İlişkileri",
  "meeting": "Toplantı",
  "meeting_to": "Toplantı",
  "meeting_from": "Şunun için Toplantı:",
  "meeting_context": "Toplantı Bağlamı",
  "meeting_context_to": "Şunun Bağlamı:",
  "meeting_context_from": "Şunun için Bağlam:",
  "agenda_item": "İlgili İçerik",
  "agenda_item_to": "İlgili İçerik",
  "agenda_item_from": "Şunun için İlgili İçerik:",
  "meeting_attachments": "Toplantı Ekleri",
  "meeting_attachments_to": "Ekler",
  "meeting_attachments_from": "Ekler",
  "decision": "Anlaşmayı yakalama kararı alındı",
  "decision_to": "Karar",
  "decision_from": "Şunun için Karar:",
  "decision_applies": "Karar Geçerli",
  "decision_applies_to": "Karar Şunun İçin Geçerli:",
  "decision_applies_from": "Karar Geçerlilik Tarihi:",
  "contributes_to_to": "Eylemler",
  "contributes_to_from": "Katkı sağlar"
}
